{
    "S-N": {
        "case": 1,
        "material": "LZ50 steel",
        "category": "fatigue_life",
        "n_samples": 15146,
        "columns": [
            "dataset_id",
            "lifen_cycle",
            "stress_amplitudesa_mpa",
            "runout"
        ],
        "target": null,
        "input_features": [
            "dataset_id",
            "lifen_cycle",
            "stress_amplitudesa_mpa",
            "runout"
        ],
        "physics_features": [],
        "notes": ""
    },
    "e-N": {
        "case": 2,
        "material": "SLM 316L",
        "category": "fracture_mechanics",
        "n_samples": 1840,
        "columns": [
            "dataset_id",
            "lifen_cycle",
            "strain_amplitudea_mm_mm",
            "runout"
        ],
        "target": null,
        "input_features": [
            "dataset_id",
            "lifen_cycle",
            "strain_amplitudea_mm_mm",
            "runout"
        ],
        "physics_features": [],
        "notes": ""
    },
    "dadn": {
        "case": 3,
        "material": "Al7075-T6",
        "category": "fatigue_life",
        "n_samples": 178061,
        "columns": [
            "dataset_id",
            "stress_intensity_factor_rangedeltak_mpam1_2",
            "crack_growth_rate_da_dn_m_cycle"
        ],
        "target": null,
        "input_features": [
            "dataset_id",
            "stress_intensity_factor_rangedeltak_mpam1_2",
            "crack_growth_rate_da_dn_m_cycle"
        ],
        "physics_features": [],
        "notes": ""
    },
    "parameter": {
        "case": 4,
        "material": "Al2024",
        "category": "stress_concentration",
        "n_samples": 2460,
        "columns": [
            "dataset_id",
            "title",
            "authors",
            "source_of_the_publication",
            "year_of_publication",
            "institution",
            "country_and_region",
            "funding_agency",
            "doi",
            "types_of_fatigue_data",
            "method_of_extraction",
            "name_of_the_material",
            "types_of_am",
            "am_machine",
            "power_w",
            "scan_speed_mm_s",
            "hatch_space_m",
            "layer_thickness_m",
            "preheat_temperature_c",
            "direciton_of_specimen_",
            "am_environment",
            "scan_pattern",
            "layer_scan_rotation_",
            "voltage_v",
            "current_a",
            "speed_function",
            "powder_feed_rate_g_s",
            "wire_feed_rate_mm_s",
            "types_of_feedstock",
            "size_of_feedstock_m",
            "processing_sequence_and_parameters",
            "types_of_fatigue_tests",
            "fatigue_temperature_c",
            "fatigue_environment",
            "load_ratio",
            "frequency_hz",
            "fatigue_machine",
            "fatigue_standard",
            "load_control",
            "specimens_description",
            "critical_crosssection_size_of_specimensmm",
            "stress_concentration_factor_of_specimens",
            "youngs_modulus_gpa",
            "yield_strength_mpa",
            "ultimate_tensile_strength_mpa",
            "elongation_",
            "rating_score"
        ],
        "target": null,
        "input_features": [
            "dataset_id",
            "title",
            "authors",
            "source_of_the_publication",
            "year_of_publication",
            "institution",
            "country_and_region",
            "funding_agency",
            "doi",
            "types_of_fatigue_data",
            "method_of_extraction",
            "name_of_the_material",
            "types_of_am",
            "am_machine",
            "power_w",
            "scan_speed_mm_s",
            "hatch_space_m",
            "layer_thickness_m",
            "preheat_temperature_c",
            "direciton_of_specimen_",
            "am_environment",
            "scan_pattern",
            "layer_scan_rotation_",
            "voltage_v",
            "current_a",
            "speed_function",
            "powder_feed_rate_g_s",
            "wire_feed_rate_mm_s",
            "types_of_feedstock",
            "size_of_feedstock_m",
            "processing_sequence_and_parameters",
            "types_of_fatigue_tests",
            "fatigue_temperature_c",
            "fatigue_environment",
            "load_ratio",
            "frequency_hz",
            "fatigue_machine",
            "fatigue_standard",
            "load_control",
            "specimens_description",
            "critical_crosssection_size_of_specimensmm",
            "stress_concentration_factor_of_specimens",
            "youngs_modulus_gpa",
            "yield_strength_mpa",
            "ultimate_tensile_strength_mpa",
            "elongation_",
            "rating_score"
        ],
        "physics_features": [],
        "notes": ""
    }
}